README.rst
setup.py
lib/__init__.py
lib/bus.py
lib/clk.py
lib/dbs.py
lib/err.py
lib/evt.py
lib/hdl.py
lib/itr.py
lib/ldr.py
lib/nms.py
lib/obj.py
lib/opt.py
lib/prs.py
lib/tbl.py
lib/thr.py
lib/tms.py
lib/trc.py
lib/trm.py
lib/url.py
lib/utl.py
lib/zzz.py
lib/olib.egg-info/PKG-INFO
lib/olib.egg-info/SOURCES.txt
lib/olib.egg-info/dependency_links.txt
lib/olib.egg-info/top_level.txt
test/test_json.py
test/test_obj.py